{
    "application": {
        "id": "",
        "title": "com.simple.SimpleApp.simpleapp",
        "type": "SAP_UI5_Component",
        "componentUrl": "/",
        "appUrl": "#simpleapp-Display",
        "navigationComponentName": "com.simple.SimpleApp",
        "intentSemanticObject": "simpleapp",
        "intentAction": "Display",
        "html5ApplicationName": "simpleapp",
        "HCPParentApplicationName": ""
    },
    "assignment": {
        "groups": [
            "242458df-1553-4c8d-90cf-0ab0419a1b87"
        ],
        "contentPackages": [
            "fde3eddc-1537-4dc8-a990-3ab1668ca0e8"
        ],
        "categories": []
    },
    "tile": {
        "type": "StaticTile",
        "title": "Title",
        "subtitle": "Subtitle",
        "searchKeywords": "Title,Subtitle",
        "displayIconUrl": "sap-icon://approvals",
        "displayInfoText": "",
        "size": "1x1",
        "serviceURL": "",
        "refreshInterval": ""
    }
}